lprof_ext/__init__.py
lprof_ext/cli.py
lprof_ext/exporter.py
lprof_ext/flow.py
lprof_ext/lib_prof.py
lprof_ext/profiler.py
lprof_ext/tools.py
lprof_ext-0.1.3.dist-info/METADATA
lprof_ext-0.1.3.dist-info/WHEEL
lprof_ext-0.1.3.dist-info/entry_points.txt
lprof_ext-0.1.3.dist-info/top_level.txt
lprof_ext-0.1.3.dist-info/RECORD
