Metadata-Version: 2.1
Name: lprof_ext
Version: 0.1.3
Summary: A Python script profiler using decorators for whole project directory
Author: Ruprof
Requires-Python: >=3.8
Requires-Dist: libcst>=1.0.0
Requires-Dist: line-profiler>=4.0.0
Requires-Dist: pandas>=2.0.3
